big_utils/__init__.py
big_utils/config/__init__.py
big_utils/config/config.py
big_utils/config/logging.py
big_utils/utils/__init__.py
big_utils/utils/crypto.py
big_utils/utils/jwt.py
big_utils/utils/strutil.py
big_utils-0.1.6.dist-info/METADATA
big_utils-0.1.6.dist-info/WHEEL
big_utils-0.1.6.dist-info/top_level.txt
big_utils-0.1.6.dist-info/RECORD
