Metadata-Version: 2.1
Name: big-utils
Version: 0.1.6
Summary: A collection of utilities used across multiple BIG projects
Home-page: https://bitbucket.org/pgolec/big-utils
Author: Patrick Golec
Author-email: patrick.golec@bitsinglass.com
License: MIT License
Project-URL: Wiki, https://bitbucket.org/pgolec/big-utils/wiki
Project-URL: Source, https://bitbucket.org/pgolec/big-utils/src
Keywords: BIG common shared utilities helpers
Classifier: Development Status :: 4 - Beta
Classifier: Intended Audience :: Developers
Classifier: Topic :: System :: Systems Administration
Classifier: License :: OSI Approved :: MIT License
Classifier: Programming Language :: Python :: 3
Classifier: Programming Language :: Python :: 3.9
Classifier: Programming Language :: Python :: 3 :: Only
Requires-Python: >=3.9.1, <4
Requires-Dist: PyJWT >=2.0.1
Requires-Dist: toml
Requires-Dist: pyyaml
Requires-Dist: dacite
